.DS_Store
pybps/.DS_Store
pybps/__init__.py
pybps/config.ini
pybps/core.py
pybps/util.py
pybps/postprocess/__init__.py
pybps/postprocess/daysim.py
pybps/postprocess/trnsys.py
pybps/preprocess/__init__.py
pybps/preprocess/daysim.py
pybps/preprocess/trnsys.py
pybps-0.2.2.data/scripts/pybps-script.py
pybps-0.2.2.data/scripts/pybps_daysim-exe.bat
pybps-0.2.2.data/scripts/run-pybps.py
pybps-0.2.2.dist-info/DESCRIPTION.rst
pybps-0.2.2.dist-info/METADATA
pybps-0.2.2.dist-info/RECORD
pybps-0.2.2.dist-info/WHEEL
pybps-0.2.2.dist-info/metadata.json
pybps-0.2.2.dist-info/top_level.txt
