Metadata-Version: 2.0
Name: pybps
Version: 0.2.2
Summary: A parametric simulation manager for building performance simulation projects
Home-page: http://github.com/dtavan/pybps
Author: Damien Tavan
Author-email: damien.tavan@gmail.com
License: BSD
Keywords: building performance simulation parametric TRNSYS DAYSIM
Platform: UNKNOWN
Classifier: Development Status :: 4 - Beta
Classifier: Environment :: Console
Classifier: Operating System :: Microsoft :: Windows
Classifier: License :: OSI Approved :: BSD License
Classifier: Intended Audience :: Science/Research
Classifier: Programming Language :: Python :: 2
Classifier: Programming Language :: Python :: 2.7
Classifier: Programming Language :: Python :: 3
Classifier: Programming Language :: Python :: 3.5
Classifier: Topic :: Scientific/Engineering
Requires-Dist: pandas
